{
    "@class": "com.kony.gen.viz.model.component.KVizLabel",
    "DNDConfig": null,
    "__parentReadjusting__": false,
    "_height_": {
        "type": "ref",
        "value": "preferred"
    },
    "_left_": {
        "type": "string",
        "value": "9%"
    },
    "_margin_": [
        1,
        1,
        1,
        1
    ],
    "_padding_": [
        0,
        0,
        0,
        0
    ],
    "_skin_": "sb3b6c1a27774d74a16dd4452d990394",
    "_text_": "I am from",
    "_top_": {
        "type": "string",
        "value": "26%"
    },
    "_width_": {
        "type": "ref",
        "value": "preferred"
    },
    "_wrapping_": 2,
    "android": {
        "textStyle": {
            "letterSpacing": 0,
            "strikeThrough": false
        }
    },
    "canUpdateUI": true,
    "containerweight": 100,
    "contentalignment": 4,
    "id": "Label06c92d06c2c8144",
    "info": null,
    "ipad": {
        "psp": {
            "wrapping": 2
        }
    },
    "iphone": {
        "psp": {
            "wrapping": 2
        }
    },
    "isvisible": true,
    "kuid": "85d4a04473f04798b4ed4fb6139bde74",
    "name": "kony.ui.Label",
    "parent": "flxContainerNewsAlertsKA",
    "pf": "frmNewsKA",
    "tooltip": "",
    "wType": "Label",
    "zindex": 1
}